veno/veno.py
veno/modules/config.py
veno/modules/configcustomizer.py
veno/modules/debug.py
veno/modules/debugwindow.py
veno/modules/diffwindow.py
veno/modules/engine.py
veno/modules/file.py
veno/modules/filewindow.py
veno/modules/filewindowmanager.py
veno/modules/helpwindow.py
veno/modules/keybindings.py
veno/modules/linejumpbar.py
veno/modules/linenumbers.py
veno/modules/openbar.py
veno/modules/runwindow.py
veno/modules/savebar.py
veno/modules/searchbar.py
veno/modules/syntaxhighlighting.py
veno/modules/window.py
veno/modules/windowbar.py
veno-2.0.8.dist-info/LICENSE
veno-2.0.8.dist-info/METADATA
veno-2.0.8.dist-info/WHEEL
veno-2.0.8.dist-info/entry_points.txt
veno-2.0.8.dist-info/top_level.txt
veno-2.0.8.dist-info/RECORD
