Metadata-Version: 2.1
Name: veno
Version: 2.0.8
Summary: Multi-purpose text/code editor meant for easy and vast expandability.
Home-page: UNKNOWN
License: GPLv3
Platform: UNKNOWN
License-File: LICENSE
Requires-Dist: Pygments
